master_captcha/__init__.py
master_captcha/master_captcha.py
master_captcha/base/request.py
master_captcha/dto/enum.py
master_captcha/dto/errors.py
master_captcha/dto/settings.py
master_captcha/services/anti_captcha/anti_captcha.py
master_captcha/services/anti_captcha/test.py
master_captcha/services/capmonster/capmonster.py
master_captcha/services/capmonster/test.py
master_captcha/services/rucaptcha/rucaptcha.py
master_captcha/services/xevil/xevil.py
master_captcha-0.0.4.dist-info/licenses/LICENSE
master_captcha-0.0.4.dist-info/METADATA
master_captcha-0.0.4.dist-info/WHEEL
master_captcha-0.0.4.dist-info/top_level.txt
master_captcha-0.0.4.dist-info/RECORD
