Metadata-Version: 2.4
Name: master-captcha
Version: 0.0.4
Summary: Сервис каптчи
Author-email: Limby <bogo44tor@gmail.com>
License: MIT
Requires-Python: >=3.10
License-File: LICENSE
Requires-Dist: aiohttp>=3.13.0
Requires-Dist: httpx>=0.28.1
Requires-Dist: loguru>=0.7.3
Dynamic: license-file
